ExcelAccesslib/__init__.py
ExcelAccesslib/excel_matrix_manage.py
DDExcelAccesslib-0.1.1.dist-info/METADATA
DDExcelAccesslib-0.1.1.dist-info/WHEEL
DDExcelAccesslib-0.1.1.dist-info/top_level.txt
DDExcelAccesslib-0.1.1.dist-info/RECORD
