Metadata-Version: 2.1
Name: DDExcelAccesslib
Version: 0.1.1
Summary: This lib controls Excel files for ProbeCard project
Home-page: UNKNOWN
License: CC0 1.0 Universal
Platform: UNKNOWN
Classifier: Development Status :: 4 - Beta
Classifier: Programming Language :: Python :: 3
Requires-Python: >=3
Requires-Dist: et-xmlfile (==1.1.0)
Requires-Dist: numpy (==1.23.4)
Requires-Dist: openpyxl (==3.0.10)
